{
  "media": {
    "type": "website",
    "title": "New York Times"
  },
  "data": [
    { "time": 0.0, "size": 635308 },
    { "time": 0.151, "size": 4669 },
    { "time": 0.279, "size": 11918 },
    { "time": 0.281, "size": 14097 },
    { "time": 0.282, "size": 38 },
    { "time": 0.283, "size": 60471 },
    { "time": 0.284, "size": 5074 },
    { "time": 0.369, "size": 97 },
    { "time": 0.371, "size": 133085 },
    { "time": 0.379, "size": 1834 },
    { "time": 0.456, "size": 20312 },
    { "time": 0.457, "size": 20212 },
    { "time": 0.492, "size": 28 },
    { "time": 0.514, "size": 28252 },
    { "time": 0.561, "size": 58580 },
    { "time": 0.611, "size": 75487 },
    { "time": 0.675, "size": 19503 },
    { "time": 0.696, "size": 26828 },
    { "time": 0.704, "size": 20085 },
    { "time": 0.731, "size": 2 },
    { "time": 0.771, "size": 692044 },
    { "time": 0.774, "size": 306197 },
    { "time": 0.815, "size": 8785045 },
    { "time": 0.849, "size": 26488 },
    { "time": 0.889, "size": 28276 },
    { "time": 0.911, "size": 65260 },
    { "time": 0.912, "size": 141919 },
    { "time": 0.929, "size": 14097 },
    { "time": 0.933, "size": 38 },
    { "time": 0.991, "size": 19503 },
    { "time": 0.992, "size": 138886 },
    { "time": 1.166, "size": 14576 },
    { "time": 1.237, "size": 35750 },
    { "time": 1.257, "size": 87948 },
    { "time": 1.277, "size": 135329 },
    { "time": 1.631, "size": 35393 },
    { "time": 1.649, "size": 69442 },
    { "time": 1.662, "size": 535 },
    { "time": 1.67, "size": 21414 },
    { "time": 1.677, "size": 4542 },
    { "time": 1.69, "size": 20846 },
    { "time": 1.75, "size": 62 },
    { "time": 1.781, "size": 1721 },
    { "time": 1.793, "size": 956593 },
    { "time": 1.823, "size": 131 },
    { "time": 1.889, "size": 21268 },
    { "time": 1.908, "size": 3928 },
    { "time": 1.946, "size": 131 },
    { "time": 2.149, "size": 66115 },
    { "time": 2.154, "size": 130150 },
    { "time": 2.302, "size": 226 },
    { "time": 2.318, "size": 1622 },
    { "time": 2.322, "size": 1622 },
    { "time": 2.325, "size": 1622 },
    { "time": 2.811, "size": 79531 },
    { "time": 2.814, "size": 25186 },
    { "time": 2.853, "size": 131 },
    { "time": 3.006, "size": 2 },
    { "time": 3.15, "size": 105675 },
    { "time": 3.199, "size": 667 },
    { "time": 3.208, "size": 42 },
    { "time": 3.284, "size": 83769 },
    { "time": 3.285, "size": 1842 },
    { "time": 3.385, "size": 4061 },
    { "time": 3.404, "size": 5058 },
    { "time": 3.649, "size": 29076 },
    { "time": 3.698, "size": 26448 },
    { "time": 4.079, "size": 1671 },
    { "time": 4.182, "size": 1648 },
    { "time": 4.187, "size": 148737 },
    { "time": 4.502, "size": 14 },
    { "time": 4.815, "size": 14 },
    { "time": 12.327, "size": 2 },
    { "time": 17.813, "size": 266138 },
    { "time": 17.814, "size": 13845 },
    { "time": 17.816, "size": 85332 },
    { "time": 18.009, "size": 77974 },
    { "time": 18.222, "size": 41047 },
    { "time": 18.229, "size": 41298 },
    { "time": 18.254, "size": 17288 },
    { "time": 18.255, "size": 32912 },
    { "time": 18.256, "size": 35256 },
    { "time": 18.257, "size": 16790 },
    { "time": 18.264, "size": 10614 },
    { "time": 18.289, "size": 20136 },
    { "time": 18.361, "size": 40036 },
    { "time": 18.538, "size": 16958 },
    { "time": 18.539, "size": 51616 },
    { "time": 18.54, "size": 11152 },
    { "time": 18.892, "size": 25554 },
    { "time": 22.329, "size": 14048 }
  ]
}
